MANIFEST.in
fastentrypoints.py
requirements.txt
setup.cfg
setup.py
iocage/__init__.py
iocage.egg-info/PKG-INFO
iocage.egg-info/SOURCES.txt
iocage.egg-info/dependency_links.txt
iocage.egg-info/entry_points.txt
iocage.egg-info/requires.txt
iocage.egg-info/top_level.txt
iocage/cli/__init__.py
iocage/cli/activate.py
iocage/cli/console.py
iocage/cli/create.py
iocage/cli/destroy.py
iocage/cli/exec.py
iocage/cli/fetch.py
iocage/cli/get.py
iocage/cli/list.py
iocage/cli/rename.py
iocage/cli/set.py
iocage/cli/start.py
iocage/cli/stop.py
iocage/lib/Datasets.py
iocage/lib/DevfsRules.py
iocage/lib/Distribution.py
iocage/lib/Filter.py
iocage/lib/Host.py
iocage/lib/Jail.py
iocage/lib/Jails.py
iocage/lib/LaunchableResource.py
iocage/lib/Logger.py
iocage/lib/Network.py
iocage/lib/NetworkInterface.py
iocage/lib/NullFSBasejailStorage.py
iocage/lib/Prompts.py
iocage/lib/Release.py
iocage/lib/Releases.py
iocage/lib/Resource.py
iocage/lib/StandaloneJailStorage.py
iocage/lib/Storage.py
iocage/lib/Types.py
iocage/lib/ZFS.py
iocage/lib/ZFSBasejailStorage.py
iocage/lib/ZFSShareStorage.py
iocage/lib/__init__.py
iocage/lib/errors.py
iocage/lib/events.py
iocage/lib/helpers.py
iocage/lib/Config/Dataset.py
iocage/lib/Config/File.py
iocage/lib/Config/JailConfigProperty.py
iocage/lib/Config/Prototype.py
iocage/lib/Config/__init__.py
iocage/lib/Config/Jail/BaseConfig.py
iocage/lib/Config/Jail/Defaults.py
iocage/lib/Config/Jail/JailConfig.py
iocage/lib/Config/Jail/JailConfigProperties.py
iocage/lib/Config/Jail/JailConfigSpecialProperty.py
iocage/lib/Config/Jail/Property.py
iocage/lib/Config/Jail/__init__.py
iocage/lib/Config/Jail/File/Fstab.py
iocage/lib/Config/Jail/File/Prototype.py
iocage/lib/Config/Jail/File/RCConf.py
iocage/lib/Config/Jail/File/__init__.py
iocage/lib/Config/Jail/Properties/Addresses.py
iocage/lib/Config/Jail/Properties/Interfaces.py
iocage/lib/Config/Jail/Properties/Resolver.py
iocage/lib/Config/Jail/Properties/__init__.py
iocage/lib/Config/Resource/ResourceConfig.py
iocage/lib/Config/Resource/__init__.py
iocage/lib/Config/Type/JSON.py
iocage/lib/Config/Type/UCL.py
iocage/lib/Config/Type/ZFS.py
iocage/lib/Config/Type/__init__.py
rc.d/ioc